{
  "records": [
    {
      "id": 1808,
      "work_order_id": 994,
      "payment_date": "2025-11-22",
      "payment_method": "efectivo",
      "payment": "Yamileth",
      "user_log_registration": 2800,
      "note": "ROC 31268 CANCELACION ",
      "sincronizado": 0,
      "is_deleted": 0
    },
    {
      "id": 1809,
      "work_order_id": 994,
      "payment_date": "2025-11-22",
      "payment_method": "efectivo",
      "payment": "Yamileth",
      "user_log_registration": 2800,
      "note": "ROC 31268 CANCELACION ",
      "sincronizado": 0,
      "is_deleted": 0
    },
    {
      "id": 1810,
      "work_order_id": 1016,
      "payment_date": "2025-11-22",
      "payment_method": "efectivo",
      "payment": "Yamileth",
      "user_log_registration": 1700,
      "note": "ROC 31269 CANCELACION ",
      "sincronizado": 0,
      "is_deleted": 0
    },
    {
      "id": 1811,
      "work_order_id": 36763,
      "payment_date": "2025-11-22",
      "payment_method": "efectivo",
      "payment": "Yamileth",
      "user_log_registration": 800,
      "note": "ROC 31270 CANCELACION",
      "sincronizado": 0,
      "is_deleted": 0
    },
    {
      "id": 1812,
      "work_order_id": 994,
      "payment_date": "2025-11-22",
      "payment_method": "efectivo",
      "payment": "Yamileth",
      "user_log_registration": 2800,
      "note": "ROC 31268 CANCELACION",
      "sincronizado": 0,
      "is_deleted": 0
    },
    {
      "id": 1813,
      "work_order_id": 1024,
      "payment_date": "2025-11-22",
      "payment_method": "efectivo",
      "payment": "Yamileth",
      "user_log_registration": 3800,
      "note": "ROC 31278 CANCELACION ",
      "sincronizado": 0,
      "is_deleted": 0
    },
    {
      "id": 1814,
      "work_order_id": 1020,
      "payment_date": "2025-11-22",
      "payment_method": "tarjeta",
      "payment": "Yamileth",
      "user_log_registration": 1800,
      "note": "ROC 31277 CANCELACION",
      "sincronizado": 0,
      "is_deleted": 0
    },
    {
      "id": 1815,
      "work_order_id": 946,
      "payment_date": "2025-11-22",
      "payment_method": "tarjeta",
      "payment": "Yamileth",
      "user_log_registration": 500,
      "note": "ROC 31276 CANCELACION ",
      "sincronizado": 0,
      "is_deleted": 0
    },
    {
      "id": 1816,
      "work_order_id": 1050,
      "payment_date": "2025-11-22",
      "payment_method": "efectivo",
      "payment": "Yamileth",
      "user_log_registration": 600,
      "note": "ROC 31275 CANCELACION",
      "sincronizado": 0,
      "is_deleted": 0
    },
    {
      "id": 1817,
      "work_order_id": 1049,
      "payment_date": "2025-11-22",
      "payment_method": "tarjeta",
      "payment": "Yamileth",
      "user_log_registration": 4000,
      "note": "ROC 31274 CANCELACION ",
      "sincronizado": 0,
      "is_deleted": 0
    },
    {
      "id": 1818,
      "work_order_id": 36767,
      "payment_date": "2025-11-22",
      "payment_method": "efectivo",
      "payment": "Yamileth",
      "user_log_registration": 500,
      "note": "ROC 31273 CANCELACIONN",
      "sincronizado": 0,
      "is_deleted": 0
    },
    {
      "id": 1819,
      "work_order_id": 1034,
      "payment_date": "2025-11-22",
      "payment_method": "transferencia",
      "payment": "Yamileth",
      "user_log_registration": 500,
      "note": "ROC 31272 CANCELACION ",
      "sincronizado": 0,
      "is_deleted": 0
    },
    {
      "id": 1820,
      "work_order_id": 36772,
      "payment_date": "2025-11-22",
      "payment_method": "tarjeta",
      "payment": "Yamileth",
      "user_log_registration": 1500,
      "note": "ROC 31271 CANCELACION",
      "sincronizado": 0,
      "is_deleted": 0
    },
    {
      "id": 1821,
      "work_order_id": 1053,
      "payment_date": "2025-11-24",
      "payment_method": "efectivo",
      "payment": "Yamileth",
      "user_log_registration": 3700,
      "note": "ROC 31279 CANCELACION ",
      "sincronizado": 0,
      "is_deleted": 0
    },
    {
      "id": 1822,
      "work_order_id": 1055,
      "payment_date": "2025-11-24",
      "payment_method": "transferencia",
      "payment": "Yamileth",
      "user_log_registration": 3450,
      "note": "ROC 31280 CANCELACION ",
      "sincronizado": 0,
      "is_deleted": 0
    },
    {
      "id": 1823,
      "work_order_id": 1058,
      "payment_date": "2025-11-24",
      "payment_method": "efectivo",
      "payment": "Yamileth",
      "user_log_registration": 1500,
      "note": "ROC 31281 CANCELACION ",
      "sincronizado": 0,
      "is_deleted": 0
    },
    {
      "id": 1824,
      "work_order_id": 1059,
      "payment_date": "2025-11-24",
      "payment_method": "efectivo",
      "payment": "Yamileth",
      "user_log_registration": 600,
      "note": "ROC 31282 CANCELACION ",
      "sincronizado": 0,
      "is_deleted": 0
    },
    {
      "id": 1825,
      "work_order_id": 1061,
      "payment_date": "2025-11-24",
      "payment_method": "efectivo",
      "payment": "Yamileth",
      "user_log_registration": 700,
      "note": "ROC 31283 CANCELACION ",
      "sincronizado": 0,
      "is_deleted": 0
    },
    {
      "id": 1826,
      "work_order_id": 1027,
      "payment_date": "2025-11-24",
      "payment_method": "tarjeta",
      "payment": "Yamileth",
      "user_log_registration": 700,
      "note": "ROC 31284 CANCELACION ",
      "sincronizado": 0,
      "is_deleted": 0
    },
    {
      "id": 1827,
      "work_order_id": 36773,
      "payment_date": "2025-11-24",
      "payment_method": "tarjeta",
      "payment": "Yamileth",
      "user_log_registration": 1600,
      "note": "ROC 31285 CANCELACION ",
      "sincronizado": 0,
      "is_deleted": 0
    },
    {
      "id": 1828,
      "work_order_id": 1063,
      "payment_date": "2025-11-24",
      "payment_method": "tarjeta",
      "payment": "Yamileth",
      "user_log_registration": 2200,
      "note": "ROC 31286 CANCELACION ",
      "sincronizado": 0,
      "is_deleted": 0
    },
    {
      "id": 1829,
      "work_order_id": 1006,
      "payment_date": "2025-11-24",
      "payment_method": "transferencia",
      "payment": "Yamileth",
      "user_log_registration": 700,
      "note": "ROC 31287 CANCELACION ",
      "sincronizado": 0,
      "is_deleted": 0
    },
    {
      "id": 1830,
      "work_order_id": 1066,
      "payment_date": "2025-11-24",
      "payment_method": "efectivo",
      "payment": "Yamileth",
      "user_log_registration": 1600,
      "note": "ROC 31288 CANCELACION",
      "sincronizado": 0,
      "is_deleted": 0
    },
    {
      "id": 1831,
      "work_order_id": 1021,
      "payment_date": "2025-11-24",
      "payment_method": "efectivo",
      "payment": "Yamileth",
      "user_log_registration": 2000,
      "note": "ROC 31289 CANCELACION ",
      "sincronizado": 0,
      "is_deleted": 0
    },
    {
      "id": 1832,
      "work_order_id": 36760,
      "payment_date": "2025-11-24",
      "payment_method": "tarjeta",
      "payment": "Yamileth",
      "user_log_registration": 700,
      "note": "ROC 31290 CANCELACION ",
      "sincronizado": 0,
      "is_deleted": 0
    },
    {
      "id": 1833,
      "work_order_id": 36771,
      "payment_date": "2025-11-24",
      "payment_method": "efectivo",
      "payment": "Yamileth",
      "user_log_registration": 1800,
      "note": "ROC 31291 CANCELACION ",
      "sincronizado": 0,
      "is_deleted": 0
    },
    {
      "id": 1834,
      "work_order_id": 1044,
      "payment_date": "2025-11-24",
      "payment_method": "transferencia",
      "payment": "Yamileth",
      "user_log_registration": 400,
      "note": "ROC 31292 CANCELACION ",
      "sincronizado": 0,
      "is_deleted": 0
    },
    {
      "id": 1835,
      "work_order_id": 36756,
      "payment_date": "2025-11-24",
      "payment_method": "transferencia",
      "payment": "Yamileth",
      "user_log_registration": 800,
      "note": "ROC 31293 CANCELACION ",
      "sincronizado": 0,
      "is_deleted": 0
    },
    {
      "id": 1836,
      "work_order_id": 1041,
      "payment_date": "2025-11-24",
      "payment_method": "tarjeta",
      "payment": "Yamileth",
      "user_log_registration": 450,
      "note": "ROC 31294 CANCELACION ",
      "sincronizado": 0,
      "is_deleted": 0
    },
    {
      "id": 1837,
      "work_order_id": 1060,
      "payment_date": "2025-11-25",
      "payment_method": "efectivo",
      "payment": "Yamileth",
      "user_log_registration": 700,
      "note": "ROC 31295 CANCELACION ",
      "sincronizado": 0,
      "is_deleted": 0
    },
    {
      "id": 1838,
      "work_order_id": 1060,
      "payment_date": "2025-11-25",
      "payment_method": "efectivo",
      "payment": "Yamileth",
      "user_log_registration": 700,
      "note": "ROC 31295 CANCELACION ",
      "sincronizado": 0,
      "is_deleted": 0
    },
    {
      "id": 1839,
      "work_order_id": 1072,
      "payment_date": "2025-11-25",
      "payment_method": "efectivo",
      "payment": "Yamileth",
      "user_log_registration": 1600,
      "note": "ROC 31296 CANCELACION ",
      "sincronizado": 0,
      "is_deleted": 0
    },
    {
      "id": 1840,
      "work_order_id": 1018,
      "payment_date": "2025-11-25",
      "payment_method": "transferencia",
      "payment": "Yamileth",
      "user_log_registration": 100,
      "note": "ROC 31297 ADELANTO",
      "sincronizado": 0,
      "is_deleted": 0
    },
    {
      "id": 1841,
      "work_order_id": 1018,
      "payment_date": "2025-11-25",
      "payment_method": "efectivo",
      "payment": "Yamileth",
      "user_log_registration": 1000,
      "note": "ROC 31298 CANCELACION ",
      "sincronizado": 0,
      "is_deleted": 0
    },
    {
      "id": 1842,
      "work_order_id": 1040,
      "payment_date": "2025-11-25",
      "payment_method": "efectivo",
      "payment": "Yamileth",
      "user_log_registration": 1600,
      "note": "ROC 31299 CANCELACION ",
      "sincronizado": 0,
      "is_deleted": 0
    },
    {
      "id": 1843,
      "work_order_id": 1036,
      "payment_date": "2025-11-25",
      "payment_method": "tarjeta",
      "payment": "Yamileth",
      "user_log_registration": 1500,
      "note": "ROC 31301 CANCELACION ",
      "sincronizado": 0,
      "is_deleted": 0
    },
    {
      "id": 1844,
      "work_order_id": 36775,
      "payment_date": "2025-11-25",
      "payment_method": "transferencia",
      "payment": "Yamileth",
      "user_log_registration": 8212,
      "note": "ROC 31302 ADELANTO",
      "sincronizado": 0,
      "is_deleted": 0
    },
    {
      "id": 1845,
      "work_order_id": 36776,
      "payment_date": "2025-11-25",
      "payment_method": "efectivo",
      "payment": "Yamileth",
      "user_log_registration": 1600,
      "note": "ROC 31303 CANCELACION ",
      "sincronizado": 0,
      "is_deleted": 0
    },
    {
      "id": 1846,
      "work_order_id": 1019,
      "payment_date": "2025-11-25",
      "payment_method": "efectivo",
      "payment": "Yamileth",
      "user_log_registration": 2500,
      "note": "ROC 31304 CANCELACION ",
      "sincronizado": 0,
      "is_deleted": 0
    },
    {
      "id": 1847,
      "work_order_id": 1078,
      "payment_date": "2025-11-25",
      "payment_method": "tarjeta",
      "payment": "Yamileth",
      "user_log_registration": 2300,
      "note": "ROC 31305 ADELANTO",
      "sincronizado": 0,
      "is_deleted": 0
    },
    {
      "id": 1848,
      "work_order_id": 1079,
      "payment_date": "2025-11-25",
      "payment_method": "transferencia",
      "payment": "Yamileth",
      "user_log_registration": 2100,
      "note": "ROC 31306 ADELANTO",
      "sincronizado": 0,
      "is_deleted": 0
    },
    {
      "id": 1849,
      "work_order_id": 1081,
      "payment_date": "2025-11-25",
      "payment_method": "efectivo",
      "payment": "Yamileth",
      "user_log_registration": 5200,
      "note": "ROC 31307 CANCELACION ",
      "sincronizado": 0,
      "is_deleted": 0
    },
    {
      "id": 1850,
      "work_order_id": 1035,
      "payment_date": "2025-11-25",
      "payment_method": "efectivo",
      "payment": "Yamileth",
      "user_log_registration": 4000,
      "note": "ROC 31308 CANCELACION",
      "sincronizado": 0,
      "is_deleted": 0
    },
    {
      "id": 1851,
      "work_order_id": 1080,
      "payment_date": "2025-11-25",
      "payment_method": "efectivo",
      "payment": "Yamileth",
      "user_log_registration": 4600,
      "note": "ROC 31309 CANCELACION ",
      "sincronizado": 0,
      "is_deleted": 0
    },
    {
      "id": 1852,
      "work_order_id": 1051,
      "payment_date": "2025-11-25",
      "payment_method": "transferencia",
      "payment": "Yamileth",
      "user_log_registration": 1000,
      "note": "ROC 31310 CANCELACION ",
      "sincronizado": 0,
      "is_deleted": 0
    },
    {
      "id": 1853,
      "work_order_id": 1013,
      "payment_date": "2025-11-25",
      "payment_method": "tarjeta",
      "payment": "Yamileth",
      "user_log_registration": 5700,
      "note": "ROC 31311 CANCELACION ",
      "sincronizado": 0,
      "is_deleted": 0
    },
    {
      "id": 1854,
      "work_order_id": 1039,
      "payment_date": "2025-11-25",
      "payment_method": "efectivo",
      "payment": "Yamileth",
      "user_log_registration": 700,
      "note": "ROC 31312 CANCELACION ",
      "sincronizado": 0,
      "is_deleted": 0
    },
    {
      "id": 1855,
      "work_order_id": 1082,
      "payment_date": "2025-11-25",
      "payment_method": "efectivo",
      "payment": "Yamileth",
      "user_log_registration": 3200,
      "note": "ROC 31313 CANCELACION ",
      "sincronizado": 0,
      "is_deleted": 0
    },
    {
      "id": 1856,
      "work_order_id": 1083,
      "payment_date": "2025-11-25",
      "payment_method": "tarjeta",
      "payment": "Yamileth",
      "user_log_registration": 3500,
      "note": "ROC 31314 CANCELACION",
      "sincronizado": 0,
      "is_deleted": 0
    },
    {
      "id": 1857,
      "work_order_id": 1047,
      "payment_date": "2025-11-25",
      "payment_method": "efectivo",
      "payment": "Yamileth",
      "user_log_registration": 3400,
      "note": "ROC 31315 CANCELACION",
      "sincronizado": 0,
      "is_deleted": 0
    },
    {
      "id": 1858,
      "work_order_id": 1065,
      "payment_date": "2025-11-25",
      "payment_method": "efectivo",
      "payment": "Yamileth",
      "user_log_registration": 700,
      "note": "ROC 31316 CANCELACION ",
      "sincronizado": 0,
      "is_deleted": 0
    },
    {
      "id": 1859,
      "work_order_id": 36439,
      "payment_date": "2025-11-25",
      "payment_method": "efectivo",
      "payment": "Yamileth",
      "user_log_registration": 800,
      "note": "ROC 31317 CANCELACION ",
      "sincronizado": 0,
      "is_deleted": 0
    },
    {
      "id": 1860,
      "work_order_id": 1056,
      "payment_date": "2025-11-25",
      "payment_method": "efectivo",
      "payment": "Yamileth",
      "user_log_registration": 2800,
      "note": "ROC 31318 CANCELACION ",
      "sincronizado": 0,
      "is_deleted": 0
    },
    {
      "id": 1861,
      "work_order_id": 1057,
      "payment_date": "2025-11-25",
      "payment_method": "transferencia",
      "payment": "Yamileth",
      "user_log_registration": 3000,
      "note": "ROC 31319 CANCELACION ",
      "sincronizado": 0,
      "is_deleted": 0
    },
    {
      "id": 1862,
      "work_order_id": 1064,
      "payment_date": "2025-11-26",
      "payment_method": "efectivo",
      "payment": "Yamileth",
      "user_log_registration": 800,
      "note": "ROC 31320 CANCELACION ",
      "sincronizado": 0,
      "is_deleted": 0
    },
    {
      "id": 1863,
      "work_order_id": 36780,
      "payment_date": "2025-11-26",
      "payment_method": "efectivo",
      "payment": "Yamileth",
      "user_log_registration": 1460,
      "note": "ROC 31321 CANCELACION ",
      "sincronizado": 0,
      "is_deleted": 0
    },
    {
      "id": 1864,
      "work_order_id": 1038,
      "payment_date": "2025-11-26",
      "payment_method": "tarjeta",
      "payment": "Yamileth",
      "user_log_registration": 1000,
      "note": "ROC 31322 CANCELACION",
      "sincronizado": 0,
      "is_deleted": 0
    },
    {
      "id": 1865,
      "work_order_id": 1043,
      "payment_date": "2025-11-26",
      "payment_method": "efectivo",
      "payment": "Yamileth",
      "user_log_registration": 2800,
      "note": "ROC 31324 CANCELACION ",
      "sincronizado": 0,
      "is_deleted": 0
    },
    {
      "id": 1866,
      "work_order_id": 1089,
      "payment_date": "2025-11-26",
      "payment_method": "efectivo",
      "payment": "Yamileth",
      "user_log_registration": 1200,
      "note": "ROC 31325 CANCELACION ",
      "sincronizado": 0,
      "is_deleted": 0
    },
    {
      "id": 1867,
      "work_order_id": 1090,
      "payment_date": "2025-11-26",
      "payment_method": "efectivo",
      "payment": "Yamileth",
      "user_log_registration": 1200,
      "note": "ROC 31326 CANCELACION ",
      "sincronizado": 0,
      "is_deleted": 0
    },
    {
      "id": 1868,
      "work_order_id": 36781,
      "payment_date": "2025-11-26",
      "payment_method": "efectivo",
      "payment": "Yamileth",
      "user_log_registration": 1600,
      "note": "ROC 31327 CANCELACION ",
      "sincronizado": 0,
      "is_deleted": 0
    },
    {
      "id": 1869,
      "work_order_id": 36777,
      "payment_date": "2025-11-26",
      "payment_method": "efectivo",
      "payment": "Yamileth",
      "user_log_registration": 1800,
      "note": "ROC 31328 CANCELACION ",
      "sincronizado": 0,
      "is_deleted": 0
    },
    {
      "id": 1870,
      "work_order_id": 1074,
      "payment_date": "2025-11-26",
      "payment_method": "efectivo",
      "payment": "Yamileth",
      "user_log_registration": 2000,
      "note": "ROC 31329 CANCELACION",
      "sincronizado": 0,
      "is_deleted": 0
    },
    {
      "id": 1871,
      "work_order_id": 36762,
      "payment_date": "2025-11-26",
      "payment_method": "efectivo",
      "payment": "Yamileth",
      "user_log_registration": 2200,
      "note": "CANCELADO A DON FRANK EL 22 DE NOVIEMBRE",
      "sincronizado": 0,
      "is_deleted": 0
    },
    {
      "id": 1872,
      "work_order_id": 36778,
      "payment_date": "2025-11-26",
      "payment_method": "transferencia",
      "payment": "Yamileth",
      "user_log_registration": 500,
      "note": "ROC 31330 CANCELACION ",
      "sincronizado": 0,
      "is_deleted": 0
    },
    {
      "id": 1873,
      "work_order_id": 1077,
      "payment_date": "2025-11-26",
      "payment_method": "efectivo",
      "payment": "Yamileth",
      "user_log_registration": 2400,
      "note": "ROC 31331 CANCELACION",
      "sincronizado": 0,
      "is_deleted": 0
    },
    {
      "id": 1874,
      "work_order_id": 1075,
      "payment_date": "2025-11-26",
      "payment_method": "transferencia",
      "payment": "Yamileth",
      "user_log_registration": 2600,
      "note": "ROC 31332 CANCELACION ",
      "sincronizado": 0,
      "is_deleted": 0
    },
    {
      "id": 1875,
      "work_order_id": 1079,
      "payment_date": "2025-11-26",
      "payment_method": "transferencia",
      "payment": "Yamileth",
      "user_log_registration": 2100,
      "note": "ROC 31333 CANCELACION",
      "sincronizado": 0,
      "is_deleted": 0
    },
    {
      "id": 1876,
      "work_order_id": 36782,
      "payment_date": "2025-11-27",
      "payment_method": "transferencia",
      "payment": "Yamileth",
      "user_log_registration": 540,
      "note": "ROC 31334 CANCELACION ",
      "sincronizado": 0,
      "is_deleted": 0
    },
    {
      "id": 1877,
      "work_order_id": 1032,
      "payment_date": "2025-11-27",
      "payment_method": "efectivo",
      "payment": "Yamileth",
      "user_log_registration": 2000,
      "note": "ROC 31335 CANCELACION. DESCUENTO AUTORIZADO POR DON FRANK 27/11",
      "sincronizado": 0,
      "is_deleted": 0
    },
    {
      "id": 1878,
      "work_order_id": 36764,
      "payment_date": "2025-11-27",
      "payment_method": "efectivo",
      "payment": "Yamileth",
      "user_log_registration": 400,
      "note": "ROC 31336 CANCELACION DESCUENTO AUTORIZADO POR DON FRANK 27/11",
      "sincronizado": 0,
      "is_deleted": 0
    },
    {
      "id": 1879,
      "work_order_id": 36779,
      "payment_date": "2025-11-27",
      "payment_method": "efectivo",
      "payment": "Yamileth",
      "user_log_registration": 1600,
      "note": "ROC 31337 CANCELACION ",
      "sincronizado": 0,
      "is_deleted": 0
    },
    {
      "id": 1880,
      "work_order_id": 1097,
      "payment_date": "2025-11-27",
      "payment_method": "tarjeta",
      "payment": "Yamileth",
      "user_log_registration": 500,
      "note": "ROC 31338 ADELANTO ",
      "sincronizado": 0,
      "is_deleted": 0
    },
    {
      "id": 1881,
      "work_order_id": 36783,
      "payment_date": "2025-11-27",
      "payment_method": "efectivo",
      "payment": "Yamileth",
      "user_log_registration": 1500,
      "note": "ROC 31339 ADELANTO",
      "sincronizado": 0,
      "is_deleted": 0
    },
    {
      "id": 1882,
      "work_order_id": 36784,
      "payment_date": "2025-11-27",
      "payment_method": "tarjeta",
      "payment": "Yamileth",
      "user_log_registration": 1750,
      "note": "ROC 31340 CANCELACION ",
      "sincronizado": 0,
      "is_deleted": 0
    },
    {
      "id": 1883,
      "work_order_id": 1048,
      "payment_date": "2025-11-27",
      "payment_method": "tarjeta",
      "payment": "Yamileth",
      "user_log_registration": 400,
      "note": "ROC 31341 ADELANTO",
      "sincronizado": 0,
      "is_deleted": 0
    },
    {
      "id": 1884,
      "work_order_id": 1048,
      "payment_date": "2025-11-27",
      "payment_method": "efectivo",
      "payment": "Yamileth",
      "user_log_registration": 2000,
      "note": "ROC 31341 CANCELACION ",
      "sincronizado": 0,
      "is_deleted": 0
    },
    {
      "id": 1885,
      "work_order_id": 36770,
      "payment_date": "2025-11-27",
      "payment_method": "efectivo",
      "payment": "Yamileth",
      "user_log_registration": 700,
      "note": "ROC 31342 CANCELACION ",
      "sincronizado": 0,
      "is_deleted": 0
    },
    {
      "id": 1886,
      "work_order_id": 1100,
      "payment_date": "2025-11-27",
      "payment_method": "efectivo",
      "payment": "Yamileth",
      "user_log_registration": 1400,
      "note": "ROC 31343 CANCELACION ",
      "sincronizado": 0,
      "is_deleted": 0
    },
    {
      "id": 1887,
      "work_order_id": 1101,
      "payment_date": "2025-11-27",
      "payment_method": "efectivo",
      "payment": "Yamileth",
      "user_log_registration": 1300,
      "note": "ROC 31344 CANCELACION ",
      "sincronizado": 0,
      "is_deleted": 0
    },
    {
      "id": 1888,
      "work_order_id": 1084,
      "payment_date": "2025-11-27",
      "payment_method": "tarjeta",
      "payment": "Yamileth",
      "user_log_registration": 1500,
      "note": "ROC 31345 CANCELACION ",
      "sincronizado": 0,
      "is_deleted": 0
    },
    {
      "id": 1889,
      "work_order_id": 1087,
      "payment_date": "2025-11-27",
      "payment_method": "tarjeta",
      "payment": "Yamileth",
      "user_log_registration": 1800,
      "note": "ROC 31346 CANCELACION ",
      "sincronizado": 0,
      "is_deleted": 0
    },
    {
      "id": 1890,
      "work_order_id": 1071,
      "payment_date": "2025-11-27",
      "payment_method": "efectivo",
      "payment": "Yamileth",
      "user_log_registration": 1600,
      "note": "ROC 31347 CANCELACION",
      "sincronizado": 0,
      "is_deleted": 0
    },
    {
      "id": 1891,
      "work_order_id": 1067,
      "payment_date": "2025-11-27",
      "payment_method": "efectivo",
      "payment": "Yamileth",
      "user_log_registration": 2000,
      "note": "ROC 31348 CANCELACION ",
      "sincronizado": 0,
      "is_deleted": 0
    },
    {
      "id": 1892,
      "work_order_id": 1085,
      "payment_date": "2025-11-27",
      "payment_method": "tarjeta",
      "payment": "Yamileth",
      "user_log_registration": 1400,
      "note": "ROC 31349 CANCELACION ",
      "sincronizado": 0,
      "is_deleted": 0
    },
    {
      "id": 1893,
      "work_order_id": 1091,
      "payment_date": "2025-11-27",
      "payment_method": "transferencia",
      "payment": "Yamileth",
      "user_log_registration": 1900,
      "note": "ROC 31350 CANCELACION ",
      "sincronizado": 0,
      "is_deleted": 0
    },
    {
      "id": 1894,
      "work_order_id": 36450,
      "payment_date": "2025-11-28",
      "payment_method": "transferencia",
      "payment": "Yamileth",
      "user_log_registration": 1720,
      "note": "ROC 31351 CANCELACION",
      "sincronizado": 0,
      "is_deleted": 0
    },
    {
      "id": 1895,
      "work_order_id": 36753,
      "payment_date": "2025-11-28",
      "payment_method": "transferencia",
      "payment": "Yamileth",
      "user_log_registration": 2500,
      "note": "ROC 31352 CANCELACION",
      "sincronizado": 0,
      "is_deleted": 0
    },
    {
      "id": 1896,
      "work_order_id": 36754,
      "payment_date": "2025-11-28",
      "payment_method": "transferencia",
      "payment": "Yamileth",
      "user_log_registration": 766,
      "note": "ROC 31353 CANCELACION ",
      "sincronizado": 0,
      "is_deleted": 0
    },
    {
      "id": 1897,
      "work_order_id": 1053,
      "payment_date": "2025-11-28",
      "payment_method": "efectivo",
      "payment": "Yamileth",
      "user_log_registration": 800,
      "note": "ROC 31354 COMPLEMENTO DE TRABAJO ",
      "sincronizado": 0,
      "is_deleted": 0
    },
    {
      "id": 1898,
      "work_order_id": 1052,
      "payment_date": "2025-11-28",
      "payment_method": "tarjeta",
      "payment": "Yamileth",
      "user_log_registration": 700,
      "note": "ROC 31355 CANCELACION",
      "sincronizado": 0,
      "is_deleted": 0
    },
    {
      "id": 1899,
      "work_order_id": 36785,
      "payment_date": "2025-11-28",
      "payment_method": "tarjeta",
      "payment": "Yamileth",
      "user_log_registration": 1000,
      "note": "ROC 31356 CANCELACION ",
      "sincronizado": 0,
      "is_deleted": 0
    },
    {
      "id": 1900,
      "work_order_id": 36787,
      "payment_date": "2025-11-28",
      "payment_method": "efectivo",
      "payment": "Yamileth",
      "user_log_registration": 438,
      "note": "ROC 31357 CANCELACION ",
      "sincronizado": 0,
      "is_deleted": 0
    },
    {
      "id": 1901,
      "work_order_id": 36789,
      "payment_date": "2025-11-28",
      "payment_method": "efectivo",
      "payment": "Yamileth",
      "user_log_registration": 1000,
      "note": "ROC 31358 ADELANTO",
      "sincronizado": 0,
      "is_deleted": 0
    },
    {
      "id": 1902,
      "work_order_id": 36790,
      "payment_date": "2025-11-28",
      "payment_method": "efectivo",
      "payment": "Yamileth",
      "user_log_registration": 329,
      "note": "ROC 31359 CANCELACION ",
      "sincronizado": 0,
      "is_deleted": 0
    },
    {
      "id": 1903,
      "work_order_id": 1094,
      "payment_date": "2025-11-28",
      "payment_method": "efectivo",
      "payment": "Yamileth",
      "user_log_registration": 1500,
      "note": "ROC 31360 CANCELACION ",
      "sincronizado": 0,
      "is_deleted": 0
    },
    {
      "id": 1904,
      "work_order_id": 36792,
      "payment_date": "2025-11-28",
      "payment_method": "transferencia",
      "payment": "Yamileth",
      "user_log_registration": 5859,
      "note": "ROC 31361 CANCELACION ",
      "sincronizado": 0,
      "is_deleted": 0
    },
    {
      "id": 1905,
      "work_order_id": 1093,
      "payment_date": "2025-11-28",
      "payment_method": "efectivo",
      "payment": "Yamileth",
      "user_log_registration": 2700,
      "note": "ROC 31362 CANCELACION ",
      "sincronizado": 0,
      "is_deleted": 0
    },
    {
      "id": 1906,
      "work_order_id": 36791,
      "payment_date": "2025-11-28",
      "payment_method": "transferencia",
      "payment": "Yamileth",
      "user_log_registration": 2000,
      "note": "ROC 31363 CANCELACION ",
      "sincronizado": 0,
      "is_deleted": 0
    },
    {
      "id": 1907,
      "work_order_id": 1095,
      "payment_date": "2025-11-28",
      "payment_method": "efectivo",
      "payment": "Yamileth",
      "user_log_registration": 600,
      "note": "ROC 31364 CANCELACION ",
      "sincronizado": 0,
      "is_deleted": 0
    },
    {
      "id": 1908,
      "work_order_id": 1103,
      "payment_date": "2025-11-28",
      "payment_method": "tarjeta",
      "payment": "Yamileth",
      "user_log_registration": 2600,
      "note": "ROC 31365 CANCELACION ",
      "sincronizado": 0,
      "is_deleted": 0
    },
    {
      "id": 1909,
      "work_order_id": 1086,
      "payment_date": "2025-11-28",
      "payment_method": "tarjeta",
      "payment": "Yamileth",
      "user_log_registration": 400,
      "note": "ROC 31366 CANCELACION ",
      "sincronizado": 0,
      "is_deleted": 0
    },
    {
      "id": 1910,
      "work_order_id": 1104,
      "payment_date": "2025-11-28",
      "payment_method": "tarjeta",
      "payment": "Yamileth",
      "user_log_registration": 1400,
      "note": "ROC 31368 CANCELACION",
      "sincronizado": 0,
      "is_deleted": 0
    },
    {
      "id": 1911,
      "work_order_id": 1113,
      "payment_date": "2025-11-29",
      "payment_method": "tarjeta",
      "payment": "Yamileth",
      "user_log_registration": 3800,
      "note": "RO 31370 CANCELACION ",
      "sincronizado": 0,
      "is_deleted": 0
    }
  ],
  "timestamp": "2025-11-29T12:33:42.517975",
  "machine_id": "26830028058983"
}