{
  "records": [
    {
      "id": 4894,
      "datetime": "2025-09-30 16:52:57",
      "username": "Allisson",
      "activity": "Inicio de sesión",
      "sincronizado": 0,
      "is_deleted": 0
    },
    {
      "id": 4906,
      "datetime": "2025-09-30 17:02:34",
      "username": "admin",
      "activity": "Inicio de sesión",
      "sincronizado": 0,
      "is_deleted": 0
    },
    {
      "id": 4907,
      "datetime": "2025-09-30 17:16:15",
      "username": "Allisson",
      "activity": "Cierre de sesión",
      "sincronizado": 0,
      "is_deleted": 0
    },
    {
      "id": 4908,
      "datetime": "2025-09-30 17:20:13",
      "username": "admin",
      "activity": "Inicio de sesión",
      "sincronizado": 0,
      "is_deleted": 0
    },
    {
      "id": 4909,
      "datetime": "2025-09-30 17:23:24",
      "username": "admin",
      "activity": "Cierre de sesión",
      "sincronizado": 0,
      "is_deleted": 0
    },
    {
      "id": 4910,
      "datetime": "2025-09-30 17:23:47",
      "username": "admin",
      "activity": "Inicio de sesión",
      "sincronizado": 0,
      "is_deleted": 0
    },
    {
      "id": 4911,
      "datetime": "2025-09-30 17:36:32",
      "username": "admin",
      "activity": "Inicio de sesión",
      "sincronizado": 0,
      "is_deleted": 0
    },
    {
      "id": 4912,
      "datetime": "2025-09-30 17:39:14",
      "username": "admin",
      "activity": "Cierre de sesión",
      "sincronizado": 0,
      "is_deleted": 0
    },
    {
      "id": 4913,
      "datetime": "2025-09-30 17:45:26",
      "username": "admin",
      "activity": "Inicio de sesión",
      "sincronizado": 0,
      "is_deleted": 0
    },
    {
      "id": 4914,
      "datetime": "2025-09-30 18:25:58",
      "username": "Yamileth",
      "activity": "Inicio de sesión",
      "sincronizado": 0,
      "is_deleted": 0
    },
    {
      "id": 4915,
      "datetime": "2025-09-30 18:27:13",
      "username": "Yamileth",
      "activity": "Cierre de Sesión",
      "sincronizado": 0,
      "is_deleted": 0
    },
    {
      "id": 4916,
      "datetime": "2025-09-29 18:28:10",
      "username": "Yamileth",
      "activity": "Inicio de sesión",
      "sincronizado": 0,
      "is_deleted": 0
    },
    {
      "id": 4917,
      "datetime": "2025-09-29 18:29:22",
      "username": "Yamileth",
      "activity": "Ingreso de caja para la orden: 36224 - monto: 700",
      "sincronizado": 0,
      "is_deleted": 0
    },
    {
      "id": 4918,
      "datetime": "2025-09-29 18:29:55",
      "username": "Yamileth",
      "activity": "Ingreso de caja para la orden: 0578 - monto: 500",
      "sincronizado": 0,
      "is_deleted": 0
    },
    {
      "id": 4919,
      "datetime": "2025-09-29 18:30:24",
      "username": "Yamileth",
      "activity": "Ingreso de caja para la orden: 0579 - monto: 400",
      "sincronizado": 0,
      "is_deleted": 0
    },
    {
      "id": 4920,
      "datetime": "2025-09-29 18:31:00",
      "username": "Yamileth",
      "activity": "Ingreso de caja para la orden: 36207 - monto: 1600",
      "sincronizado": 0,
      "is_deleted": 0
    },
    {
      "id": 4921,
      "datetime": "2025-09-29 18:31:32",
      "username": "Yamileth",
      "activity": "Ingreso de caja para la orden: 36225 - monto: 2500",
      "sincronizado": 0,
      "is_deleted": 0
    },
    {
      "id": 4922,
      "datetime": "2025-09-29 18:32:42",
      "username": "Yamileth",
      "activity": "Ingreso de caja para la orden: 36228 - monto: 1600",
      "sincronizado": 0,
      "is_deleted": 0
    },
    {
      "id": 4923,
      "datetime": "2025-09-29 18:33:53",
      "username": "Yamileth",
      "activity": "Salida de caja, monto: 1600",
      "sincronizado": 0,
      "is_deleted": 0
    },
    {
      "id": 4924,
      "datetime": "2025-09-29 18:35:54",
      "username": "Yamileth",
      "activity": "Ingreso de caja para la orden: 0563 - monto: 600",
      "sincronizado": 0,
      "is_deleted": 0
    },
    {
      "id": 4925,
      "datetime": "2025-09-29 18:37:31",
      "username": "Yamileth",
      "activity": "Ingreso de caja para la orden: 0580 - monto: 1000",
      "sincronizado": 0,
      "is_deleted": 0
    },
    {
      "id": 4926,
      "datetime": "2025-09-29 18:46:42",
      "username": "Yamileth",
      "activity": "Ingreso de caja para la orden: 36187 - monto: 1500",
      "sincronizado": 0,
      "is_deleted": 0
    },
    {
      "id": 4927,
      "datetime": "2025-09-29 18:47:16",
      "username": "Yamileth",
      "activity": "Ingreso de caja para la orden: 0574 - monto: 2800",
      "sincronizado": 0,
      "is_deleted": 0
    },
    {
      "id": 4928,
      "datetime": "2025-09-29 18:47:42",
      "username": "Yamileth",
      "activity": "Salida de caja, monto: 2800",
      "sincronizado": 0,
      "is_deleted": 0
    }
  ],
  "timestamp": "2025-09-29T12:57:04.726371",
  "machine_id": "26830028058983"
}